{
  "annotations": {
    "list": [
      {
        "builtIn": 1,
        "datasource": "-- Grafana --",
        "enable": true,
        "hide": true,
        "iconColor": "rgba(0, 211, 255, 1)",
        "name": "Annotations & Alerts",
        "type": "dashboard"
      }
    ]
  },
  "description": "",
  "editable": true,
  "gnetId": 315,
  "graphTooltip": 0,
  "links": [],
  "panels": [
    {
      "collapsed": false,
      "datasource": null,
      "gridPos": {
        "h": 1,
        "w": 24,
        "x": 0,
        "y": 0
      },
      "id": 72,
      "panels": [],
      "title": "Summary",
      "type": "row"
    },
    {
      "cacheTimeout": null,
      "colorBackground": false,
      "colorValue": false,
      "colors": [
        "#299c46",
        "rgba(237, 129, 40, 0.89)",
        "#d44a3a"
      ],
      "datasource": null,
      "format": "none",
      "gauge": {
        "maxValue": 100,
        "minValue": 0,
        "show": false,
        "thresholdLabels": false,
        "thresholdMarkers": true
      },
      "gridPos": {
        "h": 2,
        "w": 4,
        "x": 0,
        "y": 1
      },
      "id": 54,
      "interval": null,
      "links": [],
      "mappingType": 1,
      "mappingTypes": [
        {
          "name": "value to text",
          "value": 1
        },
        {
          "name": "range to text",
          "value": 2
        }
      ],
      "maxDataPoints": 100,
      "nullPointMode": "connected",
      "nullText": null,
      "options": {},
      "postfix": "",
      "postfixFontSize": "50%",
      "prefix": "",
      "prefixFontSize": "50%",
      "rangeMaps": [
        {
          "from": "null",
          "text": "N/A",
          "to": "null"
        }
      ],
      "sparkline": {
        "fillColor": "rgba(31, 118, 189, 0.18)",
        "full": false,
        "lineColor": "rgb(31, 120, 193)",
        "show": false,
        "ymax": null,
        "ymin": null
      },
      "tableColumn": "",
      "targets": [
        {
          "expr": "count(min by (pod_name)(container_start_time_seconds{pod=~\"prometheus.*alertmanager-0\"}))",
          "instant": true,
          "refId": "A"
        }
      ],
      "thresholds": "",
      "timeFrom": null,
      "timeShift": null,
      "title": "CVIM-MON Stacks",
      "type": "singlestat",
      "valueFontSize": "80%",
      "valueMaps": [
        {
          "op": "=",
          "text": "N/A",
          "value": "null"
        }
      ],
      "valueName": "avg"
    },
    {
      "cacheTimeout": null,
      "colorBackground": false,
      "colorValue": false,
      "colors": [
        "#299c46",
        "rgba(237, 129, 40, 0.89)",
        "#d44a3a"
      ],
      "datasource": null,
      "format": "short",
      "gauge": {
        "maxValue": 100,
        "minValue": 0,
        "show": false,
        "thresholdLabels": false,
        "thresholdMarkers": true
      },
      "gridPos": {
        "h": 2,
        "w": 5,
        "x": 4,
        "y": 1
      },
      "id": 55,
      "interval": null,
      "links": [],
      "mappingType": 1,
      "mappingTypes": [
        {
          "name": "value to text",
          "value": 1
        },
        {
          "name": "range to text",
          "value": 2
        }
      ],
      "maxDataPoints": 100,
      "nullPointMode": "connected",
      "nullText": null,
      "options": {},
      "postfix": " cores",
      "postfixFontSize": "50%",
      "prefix": "",
      "prefixFontSize": "50%",
      "rangeMaps": [
        {
          "from": "null",
          "text": "N/A",
          "to": "null"
        }
      ],
      "sparkline": {
        "fillColor": "rgba(31, 118, 189, 0.18)",
        "full": false,
        "lineColor": "rgb(31, 120, 193)",
        "show": false,
        "ymax": null,
        "ymin": null
      },
      "tableColumn": "",
      "targets": [
        {
          "expr": "sum(rate(container_cpu_usage_seconds_total[5m]))",
          "instant": true,
          "refId": "A"
        }
      ],
      "thresholds": "",
      "timeFrom": null,
      "timeShift": null,
      "title": "All Containers CPU Usage [5m]",
      "type": "singlestat",
      "valueFontSize": "80%",
      "valueMaps": [
        {
          "op": "=",
          "text": "N/A",
          "value": "null"
        }
      ],
      "valueName": "avg"
    },
    {
      "cacheTimeout": null,
      "colorBackground": false,
      "colorValue": false,
      "colors": [
        "#299c46",
        "rgba(237, 129, 40, 0.89)",
        "#d44a3a"
      ],
      "datasource": null,
      "format": "bps",
      "gauge": {
        "maxValue": 100,
        "minValue": 0,
        "show": false,
        "thresholdLabels": false,
        "thresholdMarkers": true
      },
      "gridPos": {
        "h": 2,
        "w": 5,
        "x": 9,
        "y": 1
      },
      "id": 59,
      "interval": null,
      "links": [],
      "mappingType": 1,
      "mappingTypes": [
        {
          "name": "value to text",
          "value": 1
        },
        {
          "name": "range to text",
          "value": 2
        }
      ],
      "maxDataPoints": 100,
      "nullPointMode": "connected",
      "nullText": null,
      "options": {},
      "postfix": "",
      "postfixFontSize": "50%",
      "prefix": "",
      "prefixFontSize": "50%",
      "rangeMaps": [
        {
          "from": "null",
          "text": "N/A",
          "to": "null"
        }
      ],
      "sparkline": {
        "fillColor": "rgba(31, 118, 189, 0.18)",
        "full": false,
        "lineColor": "rgb(31, 120, 193)",
        "show": false,
        "ymax": null,
        "ymin": null
      },
      "tableColumn": "",
      "targets": [
        {
          "expr": "8 * sum(rate(container_network_receive_bytes_total{namespace=~\"$Stack\"}[5m]))",
          "instant": true,
          "refId": "A"
        }
      ],
      "thresholds": "",
      "timeFrom": null,
      "timeShift": null,
      "title": "CVIM-MON Stacks RX [5m]",
      "type": "singlestat",
      "valueFontSize": "80%",
      "valueMaps": [
        {
          "op": "=",
          "text": "N/A",
          "value": "null"
        }
      ],
      "valueName": "avg"
    },
    {
      "cacheTimeout": null,
      "colorBackground": false,
      "colorValue": false,
      "colors": [
        "#299c46",
        "rgba(237, 129, 40, 0.89)",
        "#d44a3a"
      ],
      "datasource": null,
      "format": "bps",
      "gauge": {
        "maxValue": 100,
        "minValue": 0,
        "show": false,
        "thresholdLabels": false,
        "thresholdMarkers": true
      },
      "gridPos": {
        "h": 2,
        "w": 5,
        "x": 14,
        "y": 1
      },
      "id": 61,
      "interval": null,
      "links": [],
      "mappingType": 1,
      "mappingTypes": [
        {
          "name": "value to text",
          "value": 1
        },
        {
          "name": "range to text",
          "value": 2
        }
      ],
      "maxDataPoints": 100,
      "nullPointMode": "connected",
      "nullText": null,
      "options": {},
      "postfix": "",
      "postfixFontSize": "50%",
      "prefix": "",
      "prefixFontSize": "50%",
      "rangeMaps": [
        {
          "from": "null",
          "text": "N/A",
          "to": "null"
        }
      ],
      "sparkline": {
        "fillColor": "rgba(31, 118, 189, 0.18)",
        "full": false,
        "lineColor": "rgb(31, 120, 193)",
        "show": false,
        "ymax": null,
        "ymin": null
      },
      "tableColumn": "",
      "targets": [
        {
          "expr": "8 * sum((px_network_io_received_bytes{})/scalar(avg(prometheus_target_interval_length_seconds)))",
          "instant": true,
          "refId": "A"
        }
      ],
      "thresholds": "",
      "timeFrom": null,
      "timeShift": null,
      "title": "Portworx RX [30s]",
      "type": "singlestat",
      "valueFontSize": "80%",
      "valueMaps": [
        {
          "op": "=",
          "text": "N/A",
          "value": "null"
        }
      ],
      "valueName": "avg"
    },
    {
      "cacheTimeout": null,
      "colorBackground": false,
      "colorValue": false,
      "colors": [
        "#299c46",
        "rgba(237, 129, 40, 0.89)",
        "#d44a3a"
      ],
      "datasource": null,
      "decimals": null,
      "format": "Bps",
      "gauge": {
        "maxValue": 100,
        "minValue": 0,
        "show": false,
        "thresholdLabels": false,
        "thresholdMarkers": true
      },
      "gridPos": {
        "h": 2,
        "w": 5,
        "x": 19,
        "y": 1
      },
      "id": 64,
      "interval": null,
      "links": [],
      "mappingType": 1,
      "mappingTypes": [
        {
          "name": "value to text",
          "value": 1
        },
        {
          "name": "range to text",
          "value": 2
        }
      ],
      "maxDataPoints": 100,
      "nullPointMode": "connected",
      "nullText": null,
      "options": {},
      "postfix": "",
      "postfixFontSize": "50%",
      "prefix": "",
      "prefixFontSize": "50%",
      "rangeMaps": [
        {
          "from": "null",
          "text": "N/A",
          "to": "null"
        }
      ],
      "sparkline": {
        "fillColor": "rgba(31, 118, 189, 0.18)",
        "full": false,
        "lineColor": "rgb(31, 120, 193)",
        "show": false,
        "ymax": null,
        "ymin": null
      },
      "tableColumn": "",
      "targets": [
        {
          "expr": "sum(px_volume_vol_read_bytes{})/30",
          "instant": true,
          "refId": "A"
        }
      ],
      "thresholds": "",
      "timeFrom": null,
      "timeShift": null,
      "title": "Portworx Storage Read [30s]",
      "type": "singlestat",
      "valueFontSize": "80%",
      "valueMaps": [
        {
          "op": "=",
          "text": "N/A",
          "value": "null"
        }
      ],
      "valueName": "avg"
    },
    {
      "cacheTimeout": null,
      "colorBackground": false,
      "colorValue": false,
      "colors": [
        "#299c46",
        "rgba(237, 129, 40, 0.89)",
        "#d44a3a"
      ],
      "datasource": null,
      "format": "none",
      "gauge": {
        "maxValue": 100,
        "minValue": 0,
        "show": false,
        "thresholdLabels": false,
        "thresholdMarkers": true
      },
      "gridPos": {
        "h": 2,
        "w": 4,
        "x": 0,
        "y": 3
      },
      "id": 63,
      "interval": null,
      "links": [],
      "mappingType": 1,
      "mappingTypes": [
        {
          "name": "value to text",
          "value": 1
        },
        {
          "name": "range to text",
          "value": 2
        }
      ],
      "maxDataPoints": 100,
      "nullPointMode": "connected",
      "nullText": null,
      "options": {},
      "postfix": "",
      "postfixFontSize": "50%",
      "prefix": "",
      "prefixFontSize": "50%",
      "rangeMaps": [
        {
          "from": "null",
          "text": "N/A",
          "to": "null"
        }
      ],
      "sparkline": {
        "fillColor": "rgba(31, 118, 189, 0.18)",
        "full": false,
        "lineColor": "rgb(31, 120, 193)",
        "show": false,
        "ymax": null,
        "ymin": null
      },
      "tableColumn": "",
      "targets": [
        {
          "expr": "sum(machine_cpu_cores)",
          "instant": true,
          "refId": "A"
        }
      ],
      "thresholds": "",
      "timeFrom": null,
      "timeShift": null,
      "title": "Cluster Cores",
      "type": "singlestat",
      "valueFontSize": "80%",
      "valueMaps": [
        {
          "op": "=",
          "text": "N/A",
          "value": "null"
        }
      ],
      "valueName": "avg"
    },
    {
      "cacheTimeout": null,
      "colorBackground": false,
      "colorValue": false,
      "colors": [
        "#299c46",
        "rgba(237, 129, 40, 0.89)",
        "#d44a3a"
      ],
      "datasource": null,
      "format": "short",
      "gauge": {
        "maxValue": 100,
        "minValue": 0,
        "show": false,
        "thresholdLabels": false,
        "thresholdMarkers": true
      },
      "gridPos": {
        "h": 2,
        "w": 5,
        "x": 4,
        "y": 3
      },
      "id": 56,
      "interval": null,
      "links": [],
      "mappingType": 1,
      "mappingTypes": [
        {
          "name": "value to text",
          "value": 1
        },
        {
          "name": "range to text",
          "value": 2
        }
      ],
      "maxDataPoints": 100,
      "nullPointMode": "connected",
      "nullText": null,
      "options": {},
      "postfix": " cores",
      "postfixFontSize": "50%",
      "prefix": "",
      "prefixFontSize": "50%",
      "rangeMaps": [
        {
          "from": "null",
          "text": "N/A",
          "to": "null"
        }
      ],
      "sparkline": {
        "fillColor": "rgba(31, 118, 189, 0.18)",
        "full": false,
        "lineColor": "rgb(31, 120, 193)",
        "show": false,
        "ymax": null,
        "ymin": null
      },
      "tableColumn": "",
      "targets": [
        {
          "expr": "sum(rate(container_cpu_usage_seconds_total{namespace=~\"$Stack\"}[5m]))",
          "instant": true,
          "refId": "A"
        }
      ],
      "thresholds": "",
      "timeFrom": null,
      "timeShift": null,
      "title": "CVIM-MON Stacks CPU Usage [5m]",
      "type": "singlestat",
      "valueFontSize": "80%",
      "valueMaps": [
        {
          "op": "=",
          "text": "N/A",
          "value": "null"
        }
      ],
      "valueName": "avg"
    },
    {
      "cacheTimeout": null,
      "colorBackground": false,
      "colorValue": false,
      "colors": [
        "#299c46",
        "rgba(237, 129, 40, 0.89)",
        "#d44a3a"
      ],
      "datasource": null,
      "format": "bps",
      "gauge": {
        "maxValue": 100,
        "minValue": 0,
        "show": false,
        "thresholdLabels": false,
        "thresholdMarkers": true
      },
      "gridPos": {
        "h": 2,
        "w": 5,
        "x": 9,
        "y": 3
      },
      "id": 62,
      "interval": null,
      "links": [],
      "mappingType": 1,
      "mappingTypes": [
        {
          "name": "value to text",
          "value": 1
        },
        {
          "name": "range to text",
          "value": 2
        }
      ],
      "maxDataPoints": 100,
      "nullPointMode": "connected",
      "nullText": null,
      "options": {},
      "postfix": "",
      "postfixFontSize": "50%",
      "prefix": "",
      "prefixFontSize": "50%",
      "rangeMaps": [
        {
          "from": "null",
          "text": "N/A",
          "to": "null"
        }
      ],
      "sparkline": {
        "fillColor": "rgba(31, 118, 189, 0.18)",
        "full": false,
        "lineColor": "rgb(31, 120, 193)",
        "show": false,
        "ymax": null,
        "ymin": null
      },
      "tableColumn": "",
      "targets": [
        {
          "expr": "8 * sum(rate(container_network_transmit_bytes_total{namespace=~\"$Stack\"}[5m]))",
          "instant": true,
          "refId": "A"
        }
      ],
      "thresholds": "",
      "timeFrom": null,
      "timeShift": null,
      "title": "CVIM-MON Stacks TX [5m]",
      "type": "singlestat",
      "valueFontSize": "80%",
      "valueMaps": [
        {
          "op": "=",
          "text": "N/A",
          "value": "null"
        }
      ],
      "valueName": "avg"
    },
    {
      "cacheTimeout": null,
      "colorBackground": false,
      "colorValue": false,
      "colors": [
        "#299c46",
        "rgba(237, 129, 40, 0.89)",
        "#d44a3a"
      ],
      "datasource": null,
      "format": "bps",
      "gauge": {
        "maxValue": 100,
        "minValue": 0,
        "show": false,
        "thresholdLabels": false,
        "thresholdMarkers": true
      },
      "gridPos": {
        "h": 2,
        "w": 5,
        "x": 14,
        "y": 3
      },
      "id": 60,
      "interval": null,
      "links": [],
      "mappingType": 1,
      "mappingTypes": [
        {
          "name": "value to text",
          "value": 1
        },
        {
          "name": "range to text",
          "value": 2
        }
      ],
      "maxDataPoints": 100,
      "nullPointMode": "connected",
      "nullText": null,
      "options": {},
      "postfix": "",
      "postfixFontSize": "50%",
      "prefix": "",
      "prefixFontSize": "50%",
      "rangeMaps": [
        {
          "from": "null",
          "text": "N/A",
          "to": "null"
        }
      ],
      "sparkline": {
        "fillColor": "rgba(31, 118, 189, 0.18)",
        "full": false,
        "lineColor": "rgb(31, 120, 193)",
        "show": false,
        "ymax": null,
        "ymin": null
      },
      "tableColumn": "",
      "targets": [
        {
          "expr": "8 * sum((px_network_io_bytessent{})/scalar(avg(prometheus_target_interval_length_seconds)))",
          "instant": true,
          "refId": "A"
        }
      ],
      "thresholds": "",
      "timeFrom": null,
      "timeShift": null,
      "title": "Portworx TX [30s]",
      "type": "singlestat",
      "valueFontSize": "80%",
      "valueMaps": [
        {
          "op": "=",
          "text": "N/A",
          "value": "null"
        }
      ],
      "valueName": "avg"
    },
    {
      "cacheTimeout": null,
      "colorBackground": false,
      "colorValue": false,
      "colors": [
        "#73BF69",
        "rgba(237, 129, 40, 0.89)",
        "#d44a3a"
      ],
      "datasource": null,
      "decimals": null,
      "format": "Bps",
      "gauge": {
        "maxValue": 100,
        "minValue": 0,
        "show": false,
        "thresholdLabels": false,
        "thresholdMarkers": true
      },
      "gridPos": {
        "h": 2,
        "w": 5,
        "x": 19,
        "y": 3
      },
      "id": 65,
      "interval": null,
      "links": [],
      "mappingType": 1,
      "mappingTypes": [
        {
          "name": "value to text",
          "value": 1
        },
        {
          "name": "range to text",
          "value": 2
        }
      ],
      "maxDataPoints": 100,
      "nullPointMode": "connected",
      "nullText": null,
      "options": {},
      "postfix": "",
      "postfixFontSize": "50%",
      "prefix": "",
      "prefixFontSize": "50%",
      "rangeMaps": [
        {
          "from": "null",
          "text": "N/A",
          "to": "null"
        }
      ],
      "sparkline": {
        "fillColor": "rgba(31, 118, 189, 0.18)",
        "full": false,
        "lineColor": "rgb(31, 120, 193)",
        "show": true,
        "ymax": null,
        "ymin": null
      },
      "tableColumn": "",
      "targets": [
        {
          "expr": "sum(px_volume_vol_written_bytes{})/30",
          "instant": true,
          "refId": "A"
        }
      ],
      "thresholds": "",
      "timeFrom": null,
      "timeShift": null,
      "title": "Portworx Storage Write [30s]",
      "type": "singlestat",
      "valueFontSize": "80%",
      "valueMaps": [
        {
          "op": "=",
          "text": "N/A",
          "value": "null"
        }
      ],
      "valueName": "avg"
    },
    {
      "columns": [],
      "datasource": null,
      "fontSize": "100%",
      "gridPos": {
        "h": 6,
        "w": 24,
        "x": 0,
        "y": 5
      },
      "id": 58,
      "options": {},
      "pageSize": null,
      "showHeader": true,
      "sort": {
        "col": 0,
        "desc": true
      },
      "styles": [
        {
          "alias": "Stack",
          "colorMode": null,
          "colors": [
            "rgba(245, 54, 54, 0.9)",
            "rgba(237, 129, 40, 0.89)",
            "rgba(50, 172, 45, 0.97)"
          ],
          "dateFormat": "YYYY-MM-DD HH:mm:ss",
          "decimals": 2,
          "mappingType": 1,
          "pattern": "namespace",
          "thresholds": [],
          "type": "string",
          "unit": "short"
        },
        {
          "alias": "Cores",
          "colorMode": null,
          "colors": [
            "rgba(245, 54, 54, 0.9)",
            "rgba(237, 129, 40, 0.89)",
            "rgba(50, 172, 45, 0.97)"
          ],
          "dateFormat": "YYYY-MM-DD HH:mm:ss",
          "decimals": 2,
          "mappingType": 1,
          "pattern": "Value #A",
          "thresholds": [],
          "type": "number",
          "unit": "short"
        },
        {
          "alias": "Memory",
          "colorMode": null,
          "colors": [
            "rgba(245, 54, 54, 0.9)",
            "rgba(237, 129, 40, 0.89)",
            "rgba(50, 172, 45, 0.97)"
          ],
          "dateFormat": "YYYY-MM-DD HH:mm:ss",
          "decimals": 2,
          "mappingType": 1,
          "pattern": "Value #C",
          "thresholds": [],
          "type": "number",
          "unit": "bytes"
        },
        {
          "alias": "TX [5m]",
          "colorMode": null,
          "colors": [
            "rgba(245, 54, 54, 0.9)",
            "rgba(237, 129, 40, 0.89)",
            "rgba(50, 172, 45, 0.97)"
          ],
          "dateFormat": "YYYY-MM-DD HH:mm:ss",
          "decimals": 2,
          "mappingType": 1,
          "pattern": "Value #B",
          "thresholds": [],
          "type": "number",
          "unit": "bps"
        },
        {
          "alias": "RX [5m]",
          "colorMode": null,
          "colors": [
            "rgba(245, 54, 54, 0.9)",
            "rgba(237, 129, 40, 0.89)",
            "rgba(50, 172, 45, 0.97)"
          ],
          "dateFormat": "YYYY-MM-DD HH:mm:ss",
          "decimals": 2,
          "mappingType": 1,
          "pattern": "Value #D",
          "thresholds": [],
          "type": "number",
          "unit": "bps"
        },
        {
          "alias": "Storage Used",
          "colorMode": null,
          "colors": [
            "rgba(245, 54, 54, 0.9)",
            "rgba(237, 129, 40, 0.89)",
            "rgba(50, 172, 45, 0.97)"
          ],
          "dateFormat": "YYYY-MM-DD HH:mm:ss",
          "decimals": 2,
          "mappingType": 1,
          "pattern": "Value #E",
          "thresholds": [],
          "type": "number",
          "unit": "decbytes"
        },
        {
          "alias": "Storage Capacity",
          "colorMode": null,
          "colors": [
            "rgba(245, 54, 54, 0.9)",
            "rgba(237, 129, 40, 0.89)",
            "rgba(50, 172, 45, 0.97)"
          ],
          "dateFormat": "YYYY-MM-DD HH:mm:ss",
          "decimals": 2,
          "mappingType": 1,
          "pattern": "Value #F",
          "thresholds": [],
          "type": "number",
          "unit": "decbytes"
        },
        {
          "alias": "Storage Used %",
          "colorMode": "cell",
          "colors": [
            "rgba(115, 191, 105, 0)",
            "rgba(237, 129, 40, 0.89)",
            "rgba(245, 54, 54, 0.9)"
          ],
          "dateFormat": "YYYY-MM-DD HH:mm:ss",
          "decimals": 2,
          "mappingType": 1,
          "pattern": "Value #G",
          "thresholds": [
            "0.75",
            "0.9"
          ],
          "type": "number",
          "unit": "percentunit"
        },
        {
          "alias": "Storage Read ",
          "colorMode": "cell",
          "colors": [
            "rgba(115, 191, 105, 0)",
            "rgba(237, 129, 40, 0.89)",
            "rgba(245, 54, 54, 0.9)"
          ],
          "dateFormat": "YYYY-MM-DD HH:mm:ss",
          "decimals": 0,
          "mappingType": 1,
          "pattern": "Value #H",
          "thresholds": [
            "1000000",
            "10000000"
          ],
          "type": "number",
          "unit": "Bps"
        },
        {
          "alias": "Storage Write",
          "colorMode": "cell",
          "colors": [
            "rgba(115, 191, 105, 0)",
            "rgba(237, 129, 40, 0.89)",
            "rgba(245, 54, 54, 0.9)"
          ],
          "dateFormat": "YYYY-MM-DD HH:mm:ss",
          "decimals": 2,
          "mappingType": 1,
          "pattern": "Value #I",
          "thresholds": [
            "1000000",
            "10000000"
          ],
          "type": "number",
          "unit": "Bps"
        },
        {
          "alias": "IOPs",
          "colorMode": null,
          "colors": [
            "rgba(245, 54, 54, 0.9)",
            "rgba(237, 129, 40, 0.89)",
            "rgba(50, 172, 45, 0.97)"
          ],
          "dateFormat": "YYYY-MM-DD HH:mm:ss",
          "decimals": null,
          "mappingType": 1,
          "pattern": "Value #J",
          "thresholds": [],
          "type": "number",
          "unit": "short"
        },
        {
          "alias": "Uptime",
          "colorMode": null,
          "colors": [
            "rgba(245, 54, 54, 0.9)",
            "rgba(237, 129, 40, 0.89)",
            "rgba(50, 172, 45, 0.97)"
          ],
          "dateFormat": "YYYY-MM-DD HH:mm:ss",
          "decimals": 2,
          "mappingType": 1,
          "pattern": "Value #K",
          "thresholds": [],
          "type": "number",
          "unit": "s"
        },
        {
          "alias": "",
          "colorMode": null,
          "colors": [
            "rgba(245, 54, 54, 0.9)",
            "rgba(237, 129, 40, 0.89)",
            "rgba(50, 172, 45, 0.97)"
          ],
          "decimals": 2,
          "pattern": "/.*/",
          "thresholds": [],
          "type": "hidden",
          "unit": "short"
        }
      ],
      "targets": [
        {
          "expr": "sum by (namespace) (rate(container_cpu_usage_seconds_total{namespace=~\"$Stack\"}[5m]))",
          "format": "table",
          "hide": false,
          "instant": true,
          "refId": "A"
        },
        {
          "expr": "sum by (namespace) (container_memory_working_set_bytes{namespace=~\"$Stack\"})",
          "format": "table",
          "hide": false,
          "instant": true,
          "refId": "C"
        },
        {
          "expr": "8 * sum by (namespace) (rate(container_network_transmit_bytes_total{namespace=~\"$Stack\"}[5m]))",
          "format": "table",
          "hide": false,
          "instant": true,
          "refId": "B"
        },
        {
          "expr": "8 * sum by (namespace) (rate(container_network_receive_bytes_total{namespace=~\"$Stack\"}[5m]))",
          "format": "table",
          "hide": false,
          "instant": true,
          "refId": "D"
        },
        {
          "expr": "sum by (namespace) (px_volume_usage_bytes{namespace=~\"$Stack\"})",
          "format": "table",
          "hide": false,
          "instant": true,
          "refId": "E"
        },
        {
          "expr": "sum by (namespace) (px_volume_capacity_bytes{namespace=~\"$Stack\"})",
          "format": "table",
          "hide": false,
          "instant": true,
          "refId": "F"
        },
        {
          "expr": "sum by (namespace) (px_volume_usage_bytes{namespace=~\"$Stack\"})/sum by (namespace) (px_volume_capacity_bytes{namespace=~\"$Stack\"})",
          "format": "table",
          "hide": false,
          "instant": true,
          "refId": "G"
        },
        {
          "expr": "sum by (namespace) (px_volume_vol_read_bytes{namespace=~\"$Stack\"})/30",
          "format": "table",
          "hide": false,
          "instant": true,
          "refId": "H"
        },
        {
          "expr": "sum by (namespace) (px_volume_vol_written_bytes{namespace=~\"$Stack\"})/30",
          "format": "table",
          "hide": false,
          "instant": true,
          "refId": "I"
        },
        {
          "expr": "ceil(sum by (namespace) (px_volume_vol_writes{namespace=~\"$Stack\"}+px_volume_vol_reads{namespace=~\"$Stack\"})/30)",
          "format": "table",
          "hide": false,
          "instant": true,
          "refId": "J"
        },
        {
          "expr": "time() - max by (namespace)(container_start_time_seconds{pod=~\"prometheus.*alertmanager-0\"})",
          "format": "table",
          "hide": false,
          "instant": true,
          "refId": "K"
        }
      ],
      "timeFrom": null,
      "timeShift": null,
      "title": "Stack Resource Usage Summary",
      "transform": "table",
      "type": "table"
    },
    {
      "collapsed": true,
      "datasource": null,
      "gridPos": {
        "h": 1,
        "w": 24,
        "x": 0,
        "y": 11
      },
      "id": 37,
      "panels": [
        {
          "aliasColors": {},
          "bars": true,
          "dashLength": 10,
          "dashes": false,
          "datasource": null,
          "decimals": 3,
          "editable": true,
          "error": false,
          "fill": 0,
          "fillGradient": 0,
          "grid": {},
          "gridPos": {
            "h": 12,
            "w": 24,
            "x": 0,
            "y": 11
          },
          "height": "",
          "id": 51,
          "isNew": true,
          "legend": {
            "alignAsTable": true,
            "avg": true,
            "current": true,
            "hideEmpty": true,
            "hideZero": true,
            "max": true,
            "min": false,
            "rightSide": false,
            "show": true,
            "sideWidth": null,
            "sort": "current",
            "sortDesc": true,
            "total": false,
            "values": true
          },
          "lines": false,
          "linewidth": 1,
          "links": [],
          "nullPointMode": "connected",
          "options": {
            "dataLinks": []
          },
          "percentage": false,
          "pointradius": 0.5,
          "points": false,
          "renderer": "flot",
          "seriesOverrides": [],
          "spaceLength": 10,
          "stack": false,
          "steppedLine": true,
          "targets": [
            {
              "expr": "topk( 10, rate (container_cpu_usage_seconds_total{image!=\"\",name=~\"^k8s_.*\",container_name!=\"POD\"}[5m]))",
              "format": "time_series",
              "hide": false,
              "interval": "10s",
              "intervalFactor": 1,
              "legendFormat": "{{ pod_name }}: {{kubernetes_io_hostname}}",
              "metric": "container_cpu",
              "refId": "B",
              "step": 10
            }
          ],
          "thresholds": [],
          "timeFrom": null,
          "timeRegions": [],
          "timeShift": null,
          "title": "Top 10 Containers CPU Usage in Cluster [5m]",
          "tooltip": {
            "msResolution": true,
            "shared": true,
            "sort": 2,
            "value_type": "individual"
          },
          "type": "graph",
          "xaxis": {
            "buckets": null,
            "mode": "time",
            "name": null,
            "show": true,
            "values": []
          },
          "yaxes": [
            {
              "format": "none",
              "label": "cores",
              "logBase": 1,
              "max": null,
              "min": null,
              "show": true
            },
            {
              "format": "short",
              "label": null,
              "logBase": 1,
              "max": null,
              "min": null,
              "show": false
            }
          ],
          "yaxis": {
            "align": false,
            "alignLevel": null
          }
        }
      ],
      "title": "Containers CPU usage",
      "type": "row"
    },
    {
      "collapsed": true,
      "datasource": null,
      "gridPos": {
        "h": 1,
        "w": 24,
        "x": 0,
        "y": 12
      },
      "id": 43,
      "panels": [
        {
          "aliasColors": {},
          "bars": false,
          "dashLength": 10,
          "dashes": false,
          "datasource": null,
          "decimals": 2,
          "editable": true,
          "error": false,
          "fill": 1,
          "fillGradient": 0,
          "grid": {},
          "gridPos": {
            "h": 14,
            "w": 24,
            "x": 0,
            "y": 12
          },
          "id": 48,
          "isNew": true,
          "legend": {
            "alignAsTable": true,
            "avg": true,
            "current": true,
            "max": true,
            "min": true,
            "rightSide": false,
            "show": true,
            "sideWidth": 200,
            "sort": "current",
            "sortDesc": true,
            "total": false,
            "values": true
          },
          "lines": true,
          "linewidth": 1,
          "links": [],
          "nullPointMode": "connected",
          "options": {
            "dataLinks": []
          },
          "percentage": false,
          "pointradius": 5,
          "points": false,
          "renderer": "flot",
          "seriesOverrides": [
            {
              "alias": "/TX.*/",
              "transform": "negative-Y"
            }
          ],
          "spaceLength": 10,
          "stack": false,
          "steppedLine": false,
          "targets": [
            {
              "expr": "topk(5, 8 * rate (container_network_receive_bytes_total{interface=\"eth0\",pod=~\"prom.*\"}[5m]))",
              "hide": false,
              "interval": "10s",
              "intervalFactor": 1,
              "legendFormat": "RX {{ pod }} {{kubernetes_io_hostname}}",
              "metric": "network",
              "refId": "B",
              "step": 10
            },
            {
              "expr": "topk(5, 8 * rate (container_network_transmit_bytes_total{interface=\"eth0\",pod=~\"prom.*\"}[5m]))",
              "hide": false,
              "interval": "10s",
              "intervalFactor": 1,
              "legendFormat": "TX {{ pod }} {{kubernetes_io_hostname}}",
              "metric": "network",
              "refId": "A",
              "step": 10
            }
          ],
          "thresholds": [],
          "timeFrom": null,
          "timeRegions": [],
          "timeShift": null,
          "title": "Top 5 RX/TX Prometheus Containers in Cluster [5m] ",
          "tooltip": {
            "msResolution": false,
            "shared": true,
            "sort": 2,
            "value_type": "cumulative"
          },
          "type": "graph",
          "xaxis": {
            "buckets": null,
            "mode": "time",
            "name": null,
            "show": true,
            "values": []
          },
          "yaxes": [
            {
              "format": "bps",
              "label": "TX (-) / RX (+)",
              "logBase": 1,
              "max": null,
              "min": null,
              "show": true
            },
            {
              "format": "short",
              "label": null,
              "logBase": 1,
              "max": null,
              "min": null,
              "show": false
            }
          ],
          "yaxis": {
            "align": false,
            "alignLevel": null
          }
        }
      ],
      "title": "CVIM-MON Stacks Network Usage",
      "type": "row"
    },
    {
      "collapsed": true,
      "datasource": null,
      "gridPos": {
        "h": 1,
        "w": 24,
        "x": 0,
        "y": 13
      },
      "id": 69,
      "panels": [
        {
          "aliasColors": {},
          "bars": false,
          "dashLength": 10,
          "dashes": false,
          "datasource": null,
          "decimals": 2,
          "editable": true,
          "error": false,
          "fill": 1,
          "fillGradient": 0,
          "grid": {},
          "gridPos": {
            "h": 14,
            "w": 24,
            "x": 0,
            "y": 13
          },
          "id": 70,
          "isNew": true,
          "legend": {
            "alignAsTable": true,
            "avg": true,
            "current": true,
            "max": true,
            "min": true,
            "rightSide": false,
            "show": true,
            "sideWidth": 200,
            "sort": "current",
            "sortDesc": true,
            "total": false,
            "values": true
          },
          "lines": true,
          "linewidth": 1,
          "links": [],
          "nullPointMode": "connected",
          "options": {
            "dataLinks": []
          },
          "percentage": false,
          "pointradius": 5,
          "points": false,
          "renderer": "flot",
          "seriesOverrides": [
            {
              "alias": "/W/",
              "transform": "negative-Y"
            }
          ],
          "spaceLength": 10,
          "stack": false,
          "steppedLine": false,
          "targets": [
            {
              "expr": "sum by (namespace)(px_volume_vol_read_bytes{})/30",
              "hide": false,
              "interval": "10s",
              "intervalFactor": 1,
              "legendFormat": "Read {{namespace}}",
              "metric": "network",
              "refId": "B",
              "step": 10
            },
            {
              "expr": "sum by (namespace)(px_volume_vol_written_bytes{})/30",
              "hide": false,
              "interval": "10s",
              "intervalFactor": 1,
              "legendFormat": "Write {{namespace}}",
              "metric": "network",
              "refId": "A",
              "step": 10
            }
          ],
          "thresholds": [],
          "timeFrom": null,
          "timeRegions": [],
          "timeShift": null,
          "title": "Stacks Storage Usage [30s]",
          "tooltip": {
            "msResolution": false,
            "shared": true,
            "sort": 2,
            "value_type": "cumulative"
          },
          "type": "graph",
          "xaxis": {
            "buckets": null,
            "mode": "time",
            "name": null,
            "show": true,
            "values": []
          },
          "yaxes": [
            {
              "format": "Bps",
              "label": "Write (-) / Read (+)",
              "logBase": 1,
              "max": null,
              "min": null,
              "show": true
            },
            {
              "format": "short",
              "label": null,
              "logBase": 1,
              "max": null,
              "min": null,
              "show": false
            }
          ],
          "yaxis": {
            "align": false,
            "alignLevel": null
          }
        }
      ],
      "title": "CVIM-MON Stacks Storage Usage",
      "type": "row"
    },
    {
      "collapsed": true,
      "datasource": null,
      "gridPos": {
        "h": 1,
        "w": 24,
        "x": 0,
        "y": 14
      },
      "id": 46,
      "panels": [
        {
          "aliasColors": {},
          "bars": false,
          "dashLength": 10,
          "dashes": false,
          "datasource": null,
          "decimals": 2,
          "editable": true,
          "error": false,
          "fill": 1,
          "fillGradient": 0,
          "grid": {},
          "gridPos": {
            "h": 14,
            "w": 24,
            "x": 0,
            "y": 14
          },
          "id": 50,
          "isNew": true,
          "legend": {
            "alignAsTable": true,
            "avg": true,
            "current": true,
            "max": true,
            "min": true,
            "rightSide": false,
            "show": true,
            "sideWidth": 200,
            "sort": "current",
            "sortDesc": true,
            "total": false,
            "values": true
          },
          "lines": true,
          "linewidth": 1,
          "links": [],
          "nullPointMode": "connected",
          "options": {
            "dataLinks": []
          },
          "percentage": false,
          "pointradius": 5,
          "points": false,
          "renderer": "flot",
          "seriesOverrides": [
            {
              "alias": "/TX/",
              "transform": "negative-Y"
            }
          ],
          "spaceLength": 10,
          "stack": false,
          "steppedLine": false,
          "targets": [
            {
              "expr": "8 * sum(px_network_io_received_bytes{})/30",
              "hide": false,
              "interval": "10s",
              "intervalFactor": 1,
              "legendFormat": "RX",
              "metric": "network",
              "refId": "B",
              "step": 10
            },
            {
              "expr": "8 * sum(px_network_io_bytessent{})/30",
              "hide": false,
              "interval": "10s",
              "intervalFactor": 1,
              "legendFormat": "TX",
              "metric": "network",
              "refId": "A",
              "step": 10
            }
          ],
          "thresholds": [],
          "timeFrom": null,
          "timeRegions": [],
          "timeShift": null,
          "title": "Portworx Total RX/TX Network Usage in Cluster [30s]",
          "tooltip": {
            "msResolution": false,
            "shared": true,
            "sort": 2,
            "value_type": "cumulative"
          },
          "type": "graph",
          "xaxis": {
            "buckets": null,
            "mode": "time",
            "name": null,
            "show": true,
            "values": []
          },
          "yaxes": [
            {
              "format": "bps",
              "label": "TX (-) / RX (+)",
              "logBase": 1,
              "max": null,
              "min": null,
              "show": true
            },
            {
              "format": "short",
              "label": null,
              "logBase": 1,
              "max": null,
              "min": null,
              "show": false
            }
          ],
          "yaxis": {
            "align": false,
            "alignLevel": null
          }
        }
      ],
      "title": "Portworx Network Usage",
      "type": "row"
    },
    {
      "collapsed": true,
      "datasource": null,
      "gridPos": {
        "h": 1,
        "w": 24,
        "x": 0,
        "y": 15
      },
      "id": 41,
      "panels": [
        {
          "aliasColors": {},
          "bars": false,
          "dashLength": 10,
          "dashes": false,
          "datasource": null,
          "decimals": 2,
          "editable": true,
          "error": false,
          "fill": 0,
          "fillGradient": 0,
          "grid": {},
          "gridPos": {
            "h": 10,
            "w": 24,
            "x": 0,
            "y": 15
          },
          "id": 52,
          "isNew": true,
          "legend": {
            "alignAsTable": true,
            "avg": true,
            "current": true,
            "max": false,
            "min": false,
            "rightSide": false,
            "show": true,
            "sideWidth": 200,
            "sort": "current",
            "sortDesc": true,
            "total": false,
            "values": true
          },
          "lines": true,
          "linewidth": 1,
          "links": [],
          "nullPointMode": "connected",
          "options": {
            "dataLinks": []
          },
          "percentage": false,
          "pointradius": 5,
          "points": false,
          "renderer": "flot",
          "seriesOverrides": [],
          "spaceLength": 10,
          "stack": false,
          "steppedLine": true,
          "targets": [
            {
              "expr": "topk(10, sum (container_memory_working_set_bytes{image!=\"\",name=~\"^k8s_.*\",container_name!=\"POD\"}) by (pod_name,kubernetes_io_hostname))",
              "format": "time_series",
              "interval": "10s",
              "intervalFactor": 1,
              "legendFormat": "{{ pod_name }} | {{ kubernetes_io_hostname }}",
              "metric": "container_memory_usage:sort_desc",
              "refId": "A",
              "step": 10
            }
          ],
          "thresholds": [],
          "timeFrom": null,
          "timeRegions": [],
          "timeShift": null,
          "title": "Top 10 Container Memory Usage in Cluster",
          "tooltip": {
            "msResolution": false,
            "shared": true,
            "sort": 2,
            "value_type": "cumulative"
          },
          "type": "graph",
          "xaxis": {
            "buckets": null,
            "mode": "time",
            "name": null,
            "show": true,
            "values": []
          },
          "yaxes": [
            {
              "format": "bytes",
              "label": null,
              "logBase": 1,
              "max": null,
              "min": null,
              "show": true
            },
            {
              "format": "short",
              "label": null,
              "logBase": 1,
              "max": null,
              "min": null,
              "show": false
            }
          ],
          "yaxis": {
            "align": false,
            "alignLevel": null
          }
        }
      ],
      "title": "Containers memory usage",
      "type": "row"
    }
  ],
  "refresh": false,
  "schemaVersion": 20,
  "style": "dark",
  "tags": [],
  "templating": {
    "list": [
      {
        "allValue": null,
        "current": {
          "text": "All",
          "value": [
            "$__all"
          ]
        },
        "datasource": "Prometheus",
        "definition": "label_values(container_start_time_seconds, pod)",
        "hide": 2,
        "includeAll": true,
        "label": null,
        "multi": true,
        "name": "Stack",
        "options": [],
        "query": "label_values(container_start_time_seconds, pod)",
        "refresh": 2,
        "regex": "/prometheus-(.*)-alertmanager-0/",
        "skipUrlSync": false,
        "sort": 1,
        "tagValuesQuery": "",
        "tags": [],
        "tagsQuery": "",
        "type": "query",
        "useTags": false
      },
      {
        "current": {
          "text": "1",
          "value": "1"
        },
        "hide": 2,
        "label": null,
        "name": "version",
        "options": [
          {
            "selected": true,
            "text": "1",
            "value": "1"
          }
        ],
        "query": "1",
        "skipUrlSync": false,
        "type": "constant"
      }
    ]
  },
  "time": {
    "from": "now-6h",
    "to": "now"
  },
  "timepicker": {
    "refresh_intervals": [
      "5s",
      "10s",
      "30s",
      "1m",
      "5m",
      "15m",
      "30m",
      "1h",
      "2h",
      "1d"
    ],
    "time_options": [
      "5m",
      "15m",
      "1h",
      "6h",
      "12h",
      "24h",
      "2d",
      "7d",
      "30d"
    ]
  },
  "timezone": "browser",
  "title": "HA CVIM-MON Cluster Resource Usage",
  "uid": "VO58Y1qmz00",
  "version": 1
}